{"procesos": {"1": {"uuid": "ead6aa4c-4841-4eab-8287-597eb3d403ec", "language": "Italian", "voice": "Bianca", "main_question": "trivia sobre identificar profesiones a partir de emojis", "num_questions": 10, "num_options": 3, "background_music": "deporte1", "background_video": "newyork3", "fecha_creacion": "2024-08-14T16:33:05.610628+00:00", "fecha_modificacion": "2024-08-14T16:42:50.065897+00:00", "estado": "completado", "url_video": "https://trivias.luxuryroamers.com/generados/videos/ead6aa4c-4841-4eab-8287-597eb3d403ec.mp4"}, "3": {"uuid": "a0b27f8a-5e2c-49d3-bce5-f609e566a08c", "language": "Italian", "voice": "Bianca", "main_question": "trivia sobre identificar deportes a partir de emojis", "num_questions": 2, "num_options": 3, "background_music": "deporte2", "background_video": "sanfrancisco3", "fecha_creacion": "2024-08-14T17:42:21.741758+00:00", "fecha_modificacion": "2024-08-14T17:44:04.225073+00:00", "estado": "completado", "url_video": "https://trivias.luxuryroamers.com/generados/videos/a0b27f8a-5e2c-49d3-bce5-f609e566a08c.mp4"}, "4": {"uuid": "f997d36b-e831-44e4-8e2e-f3a4fb2d2305", "language": "Italian", "voice": "Bianca", "main_question": "trivia sobre identificar edificaciones a partir de emojis", "num_questions": 2, "num_options": 3, "background_music": "animada8", "background_video": "sanfrancisco1", "fecha_creacion": "2024-08-14T17:51:12.511381+00:00", "fecha_modificacion": "2024-08-14T17:52:52.013217+00:00", "estado": "completado", "url_video": "https://trivias.luxuryroamers.com/generados/videos/f997d36b-e831-44e4-8e2e-f3a4fb2d2305.mp4"}, "6": {"uuid": "4d7f9d7f-65a6-41fd-97e8-1920186c90f7", "language": "Espanol", "voice": "Pedro", "main_question": "trivia sobre identificar deportes a partir de emojis", "num_questions": 8, "num_options": 3, "background_music": "deporte3", "background_video": "montanas3", "fecha_creacion": "2024-08-14T21:39:35.221919+00:00", "fecha_modificacion": "2024-08-14T21:46:40.132256+00:00", "estado": "completado", "url_video": "https://trivias.luxuryroamers.com/generados/videos/4d7f9d7f-65a6-41fd-97e8-1920186c90f7.mp4"}, "7": {"uuid": "85d129f9-3526-4517-a4ac-c666c3218404", "language": "Espanol", "voice": "Lupe", "main_question": "trivia sobre identificar deportes a partir de emojis", "num_questions": 2, "num_options": 2, "background_music": "deporte3", "background_video": "paris1", "fecha_creacion": "2024-08-14T23:57:50.636708+00:00", "fecha_modificacion": "2024-08-14T23:59:33.193001+00:00", "estado": "completado", "url_video": "https://trivias.luxuryroamers.com/generados/videos/85d129f9-3526-4517-a4ac-c666c3218404.mp4"}, "10": {"uuid": "fc9eb9e0-d297-4e04-88aa-c08b297ce636", "language": "Espanol", "voice": "Pedro", "main_question": "trivia sobre identificar deportes a partir de emojis, a prop\u00f3sito de los Juegos Ol\u00edmpicos en Par\u00eds 2024", "num_questions": 2, "num_options": 3, "background_music": "deporte1", "background_video": "paris1", "fecha_creacion": "2024-08-15T00:55:24.885395+00:00", "fecha_modificacion": "2024-08-15T00:57:25.720179+00:00", "estado": "completado", "url_video": "https://trivias.luxuryroamers.com/generados/videos/fc9eb9e0-d297-4e04-88aa-c08b297ce636.mp4"}, "11": {"uuid": "75b84b8a-052f-477a-aa99-f5da2cae7851", "language": "Espanol", "voice": "Pedro", "main_question": "identificar deportes a partir de emojis, a prop\u00f3sito de los Juegos Ol\u00edmpicos en Par\u00eds 2024", "num_questions": 8, "num_options": 3, "background_music": "animada8", "background_video": "paris2", "fecha_creacion": "2024-08-15T01:28:48.097693+00:00", "fecha_modificacion": "2024-08-15T01:36:41.405002+00:00", "estado": "completado", "url_video": "https://trivias.luxuryroamers.com/generados/videos/75b84b8a-052f-477a-aa99-f5da2cae7851.mp4"}, "12": {"uuid": "9989f1d7-275c-40b5-aa57-6598c366baa4", "language": "Espanol", "voice": "Pedro", "main_question": "identificar tipos de edificaciones a partir de emojis", "num_questions": 4, "num_options": 3, "background_music": "animada2", "background_video": "playas2", "fecha_creacion": "2024-08-15T12:36:36.632730+00:00", "fecha_modificacion": "2024-08-15T12:41:29.765824+00:00", "estado": "completado", "url_video": "https://trivias.luxuryroamers.com/generados/videos/9989f1d7-275c-40b5-aa57-6598c366baa4.mp4"}, "13": {"uuid": "24440195-8c40-440f-82a2-5698a42d1109", "language": "Espanol", "voice": "Pedro", "main_question": "identificar tipos de edificaciones a partir de emojis", "num_questions": 4, "num_options": 3, "background_music": "deporte1", "background_video": "playas2", "fecha_creacion": "2024-08-15T13:07:34.463109+00:00", "fecha_modificacion": "2024-08-15T13:10:19.395790+00:00", "estado": "completado", "url_video": "https://trivias.luxuryroamers.com/generados/videos/24440195-8c40-440f-82a2-5698a42d1109.mp4"}, "14": {"uuid": "6cb4c5ff-512d-4d61-a363-0cbf5bddbf9f", "language": "Espanol", "voice": "Pedro", "main_question": "identificar tipos de emociones a partir de emojis", "num_questions": 3, "num_options": 3, "background_music": "animada1", "background_video": "playas2", "fecha_creacion": "2024-08-15T13:29:42.953650+00:00", "fecha_modificacion": "2024-08-15T13:31:16.870506+00:00", "estado": "completado", "url_video": "https://trivias.luxuryroamers.com/generados/videos/6cb4c5ff-512d-4d61-a363-0cbf5bddbf9f.mp4"}, "15": {"uuid": "e279d222-1294-4f8a-8c77-c2185ce98e69", "language": "English", "voice": "Joanna", "main_question": "identificar tipos de emociones a partir de emojis", "num_questions": 2, "num_options": 3, "background_music": "animada3", "background_video": "playas2", "fecha_creacion": "2024-08-15T13:32:46.171025+00:00", "fecha_modificacion": "2024-08-15T13:33:53.035354+00:00", "estado": "completado", "url_video": "https://trivias.luxuryroamers.com/generados/videos/e279d222-1294-4f8a-8c77-c2185ce98e69.mp4"}, "16": {"uuid": "73f827b2-4292-47a5-91e1-c669fd6a54ac", "language": "Espanol", "voice": "Pedro", "main_question": "identificar emociones a partir de emojis", "num_questions": 2, "num_options": 3, "background_music": "animada2", "background_video": "playas2", "fecha_creacion": "2024-08-15T14:32:46.471326+00:00", "fecha_modificacion": "2024-08-15T14:33:36.146381+00:00", "estado": "completado", "url_video": "https://trivias.luxuryroamers.com/generados/videos/73f827b2-4292-47a5-91e1-c669fd6a54ac.mp4"}, "22": {"uuid": "abbbfd4a-1f65-4fb0-960f-ae001dd1ce96", "language": "Espanol", "voice": "Pedro", "main_question": "identificar tipos de vehiculos a partir de emojis", "num_questions": 2, "num_options": 3, "background_music": "animada1", "background_video": "playas2", "fecha_creacion": "2024-08-15T18:16:13.688975+00:00", "fecha_modificacion": "2024-08-15T18:17:39.230021+00:00", "estado": "completado", "url_video": "https://trivias.luxuryroamers.com/generados/videos/abbbfd4a-1f65-4fb0-960f-ae001dd1ce96.mp4"}, "23": {"uuid": "f2404891-3c4f-47b4-b1a2-e315a21df022", "language": "Espanol", "voice": "Pedro", "main_question": "identificar tipos de vehiculos a partir de emojis", "num_questions": 2, "num_options": 3, "background_music": "animada2", "background_video": "playas2", "fecha_creacion": "2024-08-15T18:30:06.964265+00:00", "fecha_modificacion": "2024-08-15T18:31:16.901051+00:00", "estado": "completado", "url_video": "https://trivias.luxuryroamers.com/generados/videos/f2404891-3c4f-47b4-b1a2-e315a21df022.mp4"}, "26": {"uuid": "f17ef042-611e-4247-bfdf-829f3c517849", "language": "Espanol", "voice": "Pedro", "main_question": "identificar inventos a partir de emojis", "num_questions": 2, "num_options": 3, "background_music": "animada3", "background_video": "playas2", "fecha_creacion": "2024-08-15T18:49:36.255453+00:00", "fecha_modificacion": "2024-08-15T18:52:14.614694+00:00", "estado": "completado", "url_video": "https://trivias.luxuryroamers.com/generados/videos/f17ef042-611e-4247-bfdf-829f3c517849.mp4"}, "29": {"uuid": "5469bf7f-c36c-45dc-bb36-733e3aff2843", "language": "Espanol", "voice": "Pedro", "main_question": "identificar nombres de inventores a partir de emojis de sus inventos", "num_questions": 10, "num_options": 3, "background_music": "animada2", "background_video": "newyork3", "fecha_creacion": "2024-08-15T19:00:52.059574+00:00", "fecha_modificacion": "2024-08-15T19:13:07.543314+00:00", "estado": "completado", "url_video": "https://trivias.luxuryroamers.com/generados/videos/5469bf7f-c36c-45dc-bb36-733e3aff2843.mp4"}, "30": {"uuid": "be6ac5cc-a816-460b-bb46-47b5f2766fbd", "language": "French", "voice": "L\u00e9a", "main_question": "Una lista de 10 PEL\u00cdCULAS que puedan ser representados por 3 emojis secuenciales y que se respondan con una palabra", "num_questions": 2, "num_options": 3, "background_music": "animada4", "background_video": "paris2", "fecha_creacion": "2024-08-16T17:04:18.124409+00:00", "fecha_modificacion": "2024-08-16T17:04:45.534979+00:00", "estado": "error: Failed to get Polly response after 7 attempts", "url_video": "https://trivias.luxuryroamers.com/generados/videos/be6ac5cc-a816-460b-bb46-47b5f2766fbd.mp4"}, "31": {"uuid": "be032b8f-cc3f-47cb-b04e-6b2f0c67b946", "language": "French", "voice": "R\u00e9mi", "main_question": "Una lista de 10 PEL\u00cdCULAS que puedan ser representados por 3 emojis secuenciales y que se respondan con una palabra.", "num_questions": 2, "num_options": 3, "background_music": "animada3", "background_video": "sanfrancisco1", "fecha_creacion": "2024-08-16T17:07:40.538884+00:00", "fecha_modificacion": "2024-08-16T17:26:21.493699+00:00", "estado": "error: Failed to get Polly response after 7 attempts", "url_video": "https://trivias.luxuryroamers.com/generados/videos/be032b8f-cc3f-47cb-b04e-6b2f0c67b946.mp4"}, "32": {"uuid": "708514b3-6f95-4bc6-b946-58ec5e632444", "language": "French", "voice": "Lea", "main_question": "Una lista de 10 PEL\u00cdCULAS que puedan ser representados por 3 emojis secuenciales y que se respondan con una palabra.", "num_questions": 2, "num_options": 3, "background_music": "animada3", "background_video": "sanfrancisco1", "fecha_creacion": "2024-08-16T17:29:55.951154+00:00", "fecha_modificacion": "2024-08-16T17:32:22.879621+00:00", "estado": "error: [Errno 32] Broken pipe\n\nMoviePy error: FFMPEG encountered the following error while writing file ./public/generados/videos/708514b3-6f95-4bc6-b946-58ec5e632444.mp4:\n\n b''", "url_video": "https://trivias.luxuryroamers.com/generados/videos/708514b3-6f95-4bc6-b946-58ec5e632444.mp4"}, "33": {"uuid": "91d09072-362d-4515-9b18-5f1f084ac5ed", "language": "French", "voice": "Lea", "main_question": "Una lista de 10 PEL\u00cdCULAS que puedan ser representados por 3 emojis secuenciales y que se respondan con una palabra", "num_questions": 2, "num_options": 3, "background_music": "animada1", "background_video": "paris2", "fecha_creacion": "2024-08-16T17:31:47.770521+00:00", "fecha_modificacion": "2024-08-16T17:35:17.468874+00:00", "estado": "completado", "url_video": "https://trivias.luxuryroamers.com/generados/videos/91d09072-362d-4515-9b18-5f1f084ac5ed.mp4"}, "34": {"uuid": "156ef114-57ee-470d-864d-3bd0031c3e84", "language": "Espanol", "voice": "Pedro", "main_question": "Qu\u00e9 tanto sabes sobre la creaci\u00f3n del mundo seg\u00fan el libro de G\u00e9nesis.", "num_questions": 10, "num_options": 3, "background_music": "felicidad3", "background_video": "nubes1", "fecha_creacion": "2024-08-17T12:36:11.649568+00:00", "fecha_modificacion": "2024-08-17T12:36:38.029620+00:00", "estado": "error: Failed to get Polly response after 7 attempts", "url_video": "https://trivias.luxuryroamers.com/generados/videos/156ef114-57ee-470d-864d-3bd0031c3e84.mp4"}, "35": {"uuid": "b2f4b1a2-a30f-4b70-8399-d8a5326e7d7b", "language": "Espanol", "voice": "Pedro", "main_question": "Qu\u00e9 tanto sabes sobre la creaci\u00f3n del mundo seg\u00fan el libro de G\u00e9nesis.", "num_questions": 10, "num_options": 3, "background_music": "deporte3", "background_video": "nubes1", "fecha_creacion": "2024-08-17T12:38:18.050752+00:00", "fecha_modificacion": "2024-08-17T12:38:45.308908+00:00", "estado": "error: Failed to get Polly response after 7 attempts", "url_video": "https://trivias.luxuryroamers.com/generados/videos/b2f4b1a2-a30f-4b70-8399-d8a5326e7d7b.mp4"}, "36": {"uuid": "685b9ec6-fea3-4aa7-91a5-59de2f48ad43", "language": "Spanish", "voice": "Andres", "main_question": "Qu\u00e9 tanto sabes sobre la creaci\u00f3n del mundo seg\u00fan G\u00e9nesis.", "num_questions": 10, "num_options": 3, "background_music": "animada2", "background_video": "nubes1", "fecha_creacion": "2024-08-17T16:55:52.820752+00:00", "fecha_modificacion": "2024-08-17T16:56:19.460706+00:00", "estado": "error: Failed to get Polly response after 7 attempts", "url_video": "https://trivias.luxuryroamers.com/generados/videos/685b9ec6-fea3-4aa7-91a5-59de2f48ad43.mp4"}, "37": {"uuid": "3f43e1b6-7c39-424a-b2a8-d49258f36a07", "language": "Spanish", "voice": "Andres", "main_question": "Qu\u00e9 tanto sabes sobre la creaci\u00f3n del mundo seg\u00fan G\u00e9nesis.", "num_questions": 10, "num_options": 3, "background_music": "deporte4", "background_video": "nubes1", "fecha_creacion": "2024-08-17T17:02:03.402508+00:00", "fecha_modificacion": "2024-08-17T17:12:18.993865+00:00", "estado": "completado", "url_video": "https://trivias.luxuryroamers.com/generados/videos/3f43e1b6-7c39-424a-b2a8-d49258f36a07.mp4"}, "38": {"uuid": "32b95a74-b39f-409c-8505-a728939c425f", "language": "Spanish", "voice": "Penelope", "main_question": "Qu\u00e9 tanto sabes sobre la creaci\u00f3n del mundo seg\u00fan G\u00e9nesis.", "num_questions": 2, "num_options": 3, "background_music": "inspiracional1", "background_video": "nubes1", "fecha_creacion": "2024-08-17T17:58:35.457709+00:00", "fecha_modificacion": "2024-08-17T17:58:39.238970+00:00", "estado": "error: 'AudioFileClip' object has no attribute 'loop'", "url_video": "https://trivias.luxuryroamers.com/generados/videos/32b95a74-b39f-409c-8505-a728939c425f.mp4"}, "39": {"uuid": "41bf9a74-5a75-437e-b827-ef3945573fcd", "language": "Spanish", "voice": "Penelope", "main_question": "Qu\u00e9 tanto sabes sobre la creaci\u00f3n del mundo seg\u00fan G\u00e9nesis.", "num_questions": 2, "num_options": 3, "background_music": "inspiracional2", "background_video": "nubes1", "fecha_creacion": "2024-08-17T18:19:51.747914+00:00", "fecha_modificacion": "2024-08-17T18:19:56.118082+00:00", "estado": "error: Error in file ./public/assets/audios/ding.mp3, Accessing time t=1.66-1.71 seconds, with clip duration=1 seconds, ", "url_video": "https://trivias.luxuryroamers.com/generados/videos/41bf9a74-5a75-437e-b827-ef3945573fcd.mp4"}, "41": {"uuid": "e2e0849b-a695-4bbf-8cf8-ce3b5859dcc6", "language": "Spanish", "voice": "Andres", "main_question": "Qu\u00e9 tanto sabes sobre la creaci\u00f3n del mundo seg\u00fan el libro de G\u00e9nesis", "num_questions": 10, "num_options": 3, "background_music": "inspiracional4", "background_video": "nubes1", "fecha_creacion": "2024-08-17T22:44:22.185409+00:00", "fecha_modificacion": "2024-08-17T22:53:38.231127+00:00", "estado": "completado", "url_video": "https://trivias.luxuryroamers.com/generados/videos/e2e0849b-a695-4bbf-8cf8-ce3b5859dcc6.mp4"}, "42": {"uuid": "37585506-dde8-4374-b917-1693c800e5c4", "language": "Spanish", "voice": "Andres", "main_question": "Qu\u00e9 tanto sabes sobre la historia del Arca de No\u00e9", "num_questions": 2, "num_options": 3, "background_music": "inspiracional3", "background_video": "playas3", "fecha_creacion": "2024-08-18T12:31:12.561222+00:00", "fecha_modificacion": "2024-08-18T12:33:37.310273+00:00", "estado": "completado", "url_video": "https://trivias.luxuryroamers.com/generados/videos/37585506-dde8-4374-b917-1693c800e5c4.mp4"}, "43": {"uuid": "4101da71-aba0-4074-bba4-081203c2abed", "language": "Spanish", "voice": "Andres", "main_question": "Qu\u00e9 tanto sabes sobre la historia del Arca de No\u00e9.", "num_questions": 2, "num_options": 3, "background_music": "animada3", "background_video": "nubes1", "logo_path": "./public/cargados/logos/4101da71-aba0-4074-bba4-081203c2abed.png", "account_text": "@clubdelosgenios", "fecha_creacion": "2024-08-19T02:40:18.364997+00:00", "fecha_modificacion": "2024-08-19T02:42:15.455330+00:00", "estado": "completado", "url_video": "https://trivias.luxuryroamers.com/generados/videos/4101da71-aba0-4074-bba4-081203c2abed.mp4"}, "44": {"uuid": "a5efaa64-be34-45fb-9117-774833a9734b", "language": "English", "voice": "Matthew", "main_question": "Qu\u00e9 tanto sabes sobre la historia del Arca de No\u00e9.", "num_questions": 2, "num_options": 3, "background_music": "animada3", "background_video": "playas2", "logo_path": "./public/cargados/logos/a5efaa64-be34-45fb-9117-774833a9734b.png", "account_text": "@clubdelosgenios", "fecha_creacion": "2024-08-19T02:43:36.201695+00:00", "fecha_modificacion": "2024-08-19T02:47:28.822700+00:00", "estado": "completado", "url_video": "https://trivias.luxuryroamers.com/generados/videos/a5efaa64-be34-45fb-9117-774833a9734b.mp4"}, "45": {"uuid": "bb0b4393-bea0-450b-a68e-1d8e841e606b", "language": "Spanish", "voice": "Andres", "main_question": "Qu\u00e9 tanto sabes sobre la historia del Arca de No\u00e9.", "num_questions": 10, "num_options": 3, "background_music": "felicidad2", "background_video": "playas3", "logo_path": "./public/cargados/logos/bb0b4393-bea0-450b-a68e-1d8e841e606b.png", "account_text": "@clubdelosgenios", "fecha_creacion": "2024-08-19T02:47:45.247722+00:00", "fecha_modificacion": "2024-08-19T02:47:45.247722+00:00", "estado": "pendiente"}}}